<?xml version="1.0" encoding="UTF-8"?>

<beans xmlns="http://www.springframework.org/schema/beans"
	xmlns:aop="http://www.springframework.org/schema/aop"
	xmlns:xsi="http://www.w3.org/2001/XMLSchema-instance" xmlns:mvc="http://www.springframework.org/schema/mvc"
	xmlns:context="http://www.springframework.org/schema/context"
	xsi:schemaLocation="http://www.springframework.org/schema/beans http://www.springframework.org/schema/beans/spring-beans-4.0.xsd
            http://www.springframework.org/schema/context http://www.springframework.org/schema/context/spring-context-4.0.xsd
            http://www.springframework.org/schema/mvc http://www.springframework.org/schema/mvc/spring-mvc-4.0.xsd
            http://www.springframework.org/schema/aop         
     http://www.springframework.org/schema/aop/spring-aop-4.0.xsd">
	<mvc:annotation-driven
		ignore-default-model-on-redirect="true" />
	<mvc:resources mapping="/**" location="/" />
	<context:component-scan base-package="springbased.*" />
	<aop:aspectj-autoproxy />

	<bean id="viewResolver"
		class="org.springframework.web.servlet.view.InternalResourceViewResolver">
		<property name="contentType" value="text/html; charset=UTF-8" />
	</bean>

	<bean
		class="org.springframework.web.servlet.view.json.MappingJackson2JsonView">
	</bean>

	<bean id="multipartResolver"
		class="org.springframework.web.multipart.commons.CommonsMultipartResolver">
		<property name="maxUploadSize" value="10000000" />
	</bean>

	<bean name="exampleJob" class="org.springframework.scheduling.quartz.JobDetailBean">
		<property name="jobClass" value="springbased.service.job.ExampleQuartzJob" />
		<property name="jobDataAsMap">
			<map>
				<entry key="timeout" value="5" />
			</map>
		</property>
	</bean>


	<bean id="cronTrigger"
		class="org.springframework.scheduling.quartz.CronTriggerFactoryBean">
		<property name="jobDetail" ref="exampleJob" />
		<!-- run every 24 hours -->
		<property name="cronExpression" value="*/30 * * * * ?" />
		<!-- <property name="cronExpression" value="0 0 1 * * ?" /> -->
	</bean>

	<bean class="org.springframework.scheduling.quartz.SchedulerFactoryBean">
		<property name="triggers">
			<list>
				<ref bean="cronTrigger" />
			</list>
		</property>
	</bean>
</beans>